{"VwCz3ZyOTJC/1B4Hi1er3w==":"horizontal%20negativo%20amarillo.svg","XqStexa3ucYeWEdbgE9USg==":"background1.jpg","NjYtZJd3rrFODOdMq4rmiA==":"desyuno%20de%20trabajo.webp","C+EiHFrfXLdGyBvuUWM1NQ==":"desyuno%20de%20trabajo.webp","avP5oJVKM9nA5WflLUdvJA==":"desyuno%20de%20trabajo.webp","kTJiGM05iWzT7fbL1IGV4A==":"recurso%2015-609x610.png","3dgAb8UPwh/o8QJ/kgnaxw==":"shop1.jpg","jzr9nIbVK71fo9NpNmBAnw==":"imagen-filtro-negro-1.webp","So9lB1RrVHQwUMwcP9v0WA==":"img-20251213-202439603-hdr.jpg.webp","f1S57p+NdWmqiqFNUcj77A==":"bandera-1.webp","ufVj1h4B499AVfmQB+cfjw==":"bandera-2.webp","X9eJHBTU/qnbU+NASG1v7Q==":"mardelplata.webp","Pd5nISEi2pqW4mu6vum/sA==":"tirado.webp","DN0cwDxRkw2eF/2pcPQ6bQ==":"trulli-marca.webp","4c6I6IlRYh9KF9m+jKO+9w==":"trulli-alberobello.webp","28RDrkQ67fQy/PlPfEHXLQ==":"trulli-insumos1.webp","ub78Nij7QRhLlnnifyYe7w==":"trulli-insumos2.webp","zqLOH+jGtJOFWzZN5Jo6YQ==":"trulli-sorteo.webp","qCUqnno8SaVzhIRAdKBntQ==":"trulli-paleta.webp","TN1EAXS0j6ehkwDar4zKRg==":"trulli-header.webp","LKlDafx5BwKe0+NV78xV1A==":"perrosamuel.webp","sRpZsGB9chKDk1kADMLjBA==":"mockup1.webp","+jybM1rAGeLduBmOTJHgEg==":"mockup2.webp","VXSGWlURpD0meK+fTuTjaw==":"mockup3.webp","g+A1nw16Joao01SPwnFIaQ==":"gallery07.jpg","M15BOIhVX53Jn6SQyWOIoA==":"mardelplata-1.webp","k5A/L5ps1MdrghvhE2YPLA==":"jg-marca.webp","Zog9HVmHyUmmo36kMbrGyA==":"jg-gg.webp","sXBLggp7iNdPPTjmidoGow==":"jg-construccion.webp","zsFaLyWYRmEeVENuM2wYXw==":"jg-colores.webp","JdVvW9LMn8hUmPcz5Z4tQA==":"sticker-notebook.webp","aqzjtWag+6uqaFlbbsCSvA==":"jg-slogan.webp","pg9duXL2rQq0HLWErkfV2Q==":"sticker-circular.webp","JyF5Y6tbkV7WdRs7VROZmw==":"lanyard.webp","Y9mc3D1s0sX8KQpWX5PdbA==":"jg-horizontal.webp","3udIWle7ZGRUHbDPCHyo5w==":"iphone15.webp","ETHEF8ZQt7HPbEci+hq8mw==":"vidriera2.webp","OhdPrQGE6u3Wagl4BPgM0A==":"vidriera.webp","hqSgIxcmG8mw6pQk1LKUug==":"joystick.webp","9B0bBdr5Q3rdt5A0MtB7dQ==":"jg-fondo.webp","KhoQjHjWpxTqmkU4oS9BTg==":"jg-owners.webp","0s+HisV4wT/jxCVUc22D7w==":"jg-portada.webp","hZza0xYkPBIO5VdRxh5dOA==":"pendrive.webp","1ay9sHiq0gb84wJcaOiF1w==":"jg-portada-1.webp"}